LICENSE.txt
MANIFEST.in
README.rst
setup.py
nistrng/__init__.py
nistrng/functions.py
nistrng/test.py
nistrng.egg-info/PKG-INFO
nistrng.egg-info/SOURCES.txt
nistrng.egg-info/dependency_links.txt
nistrng.egg-info/requires.txt
nistrng.egg-info/top_level.txt
nistrng/sp800_22r1a/__init__.py
nistrng/sp800_22r1a/test_approximate_entropy.py
nistrng/sp800_22r1a/test_binary_matrix_rank.py
nistrng/sp800_22r1a/test_cumulative_sums.py
nistrng/sp800_22r1a/test_discrete_fourier_transform.py
nistrng/sp800_22r1a/test_frequency_within_block.py
nistrng/sp800_22r1a/test_linear_complexity.py
nistrng/sp800_22r1a/test_longest_run_ones_in_a_block.py
nistrng/sp800_22r1a/test_maurers_universal.py
nistrng/sp800_22r1a/test_monobit.py
nistrng/sp800_22r1a/test_non_overlapping_template_matching.py
nistrng/sp800_22r1a/test_overlapping_template_matching.py
nistrng/sp800_22r1a/test_random_excursion.py
nistrng/sp800_22r1a/test_random_excursion_variant.py
nistrng/sp800_22r1a/test_runs.py
nistrng/sp800_22r1a/test_serial.py