Metadata-Version: 1.1
Name: nistrng
Version: 1.2.2
Summary: NIST Test Suite for Random Number Generators - SAILab - University of Siena
Home-page: https://github.com/InsaneMonster/NistRng
Author: Luca Pasqualini
Author-email: pasqualini@diism.unisi.it
License: BSD 3-Clause
Keywords: NIST Tests RNG Random Number Generator SAILab USiena Siena SP800-22r1a
Platform: UNKNOWN
Classifier: Development Status :: 5 - Production/Stable
Classifier: License :: OSI Approved :: BSD License
Classifier: Programming Language :: Python :: 3.6
Classifier: Topic :: Security :: Cryptography
